{
  "Project 0102 has 2 APs": [
    {
      "forGroup": "http://www.knora.org/ontology/knora-admin#ProjectMember",
      "forProject": "http://rdfh.ch/projects/0102",
      "hasPermissions": [
        "ProjectResourceCreateAllPermission"
      ],
      "iri": "http://rdfh.ch/permissions/0102/8vl57gl0TA2gNxDmovrdPA"
    },
    {
      "forGroup": "http://www.knora.org/ontology/knora-admin#ProjectAdmin",
      "forProject": "http://rdfh.ch/projects/0102",
      "hasPermissions": [
        "ProjectResourceCreateAllPermission",
        "ProjectAdminAllPermission"
      ],
      "iri": "http://rdfh.ch/permissions/0102/5XXPVBlVSeOvTwm4PYfSaw"
    }
  ]
}